DIGITAL DELAY TIMER/design.sv
module delay_timer (
  input wire clk,
  input wire start,
  output wire done
);

  reg [31:0] count;
  reg done_reg;

  always @(posedge clk) begin
    if (start) begin
      count <= 32'hFFFFFFFF;  // Set delay time to 2^32 - 1 clock cycles
      done_reg <= 0;
    end
    else if (count > 0) begin
      count <= count - 1;
      done_reg <= 0;
    end
    else if (count == 0) begin
      done_reg <= 1;
    end
  end

  assign done = done_reg;

endmodule

DIGITAL DELAY TIMER/testbench.sv
module delay_timer_tb;

  reg clk;
  reg start;
  wire done;

  // Instantiate the delay_timer module
  delay_timer dut (
    .clk(clk),
    .start(start),
    .done(done)
  );

  // Clock generation
  always #5 clk = ~clk;

  // Stimulus generation
  initial begin
    clk = 0;
    start = 0;

    // Dump VCD file and variables
    $dumpfile("delay_timer_tb.vcd");
    $dumpvars(0, delay_timer_tb);

    #10 start = 1;  // Start the delay timer
    #100 start = 0; // Stop the delay timer

    #100 $finish; // End the simulation
  end

  // Monitor
  always @(posedge clk) begin
    if (done)
      $display("Delay timer done at time %0t", $time);
  end

endmodule

DIGITAL DELAY TIMER/delay_timer_tb.vcd
$date
	Sat Jun 17 10:00:33 2023
$end

$version
	Synopsys VCS version S-2021.09
$end

$timescale
	1ns
$end

$comment Csum: 1 9bbf05b62cee43c7 $end


$scope module delay_timer_tb $end
$var reg 1 ! clk $end
$var reg 1 " start $end
$var wire 1 # done $end

$scope module dut $end
$var wire 1 ! clk $end
$var wire 1 " start $end
$var wire 1 # done $end
$var reg 32 $ count [31:0] $end
$var reg 1 # done_reg $end
$upscope $end

$upscope $end

$enddefinitions $end

#0
$dumpvars
0!
x#
0"
bxxxxxxxxxxxxxxxxxxxxxxxxxxxxxxxx $
$end
#5
1!
#10
1"
0!
#15
1!
b11111111111111111111111111111111 $
0#
#20
0!
#25
1!
#30
0!
#35
1!
#40
0!
#45
1!
#50
0!
#55
1!
#60
0!
#65
1!
#70
0!
#75
1!
#80
0!
#85
1!
#90
0!
#95
1!
#100
0!
#105
1!
#110
0"
0!
#115
1!
b11111111111111111111111111111110 $
#120
0!
#125
1!
b11111111111111111111111111111101 $
#130
0!
#135
1!
b11111111111111111111111111111100 $
#140
0!
#145
1!
b11111111111111111111111111111011 $
#150
0!
#155
1!
b11111111111111111111111111111010 $
#160
0!
#165
1!
b11111111111111111111111111111001 $
#170
0!
#175
1!
b11111111111111111111111111111000 $
#180
0!
#185
1!
b11111111111111111111111111110111 $
#190
0!
#195
1!
b11111111111111111111111111110110 $
#200
0!
#205
1!
b11111111111111111111111111110101 $
